MANIFEST.in
README.md
setup.cfg
setup.py
doc/cnn.md
doc/dae.md
doc/vae.md
mozi/__init__.py
mozi/cost.py
mozi/env.py
mozi/learning_method.py
mozi/log.py
mozi/model.py
mozi/train_object.py
mozi/weight_init.py
mozi.egg-info/PKG-INFO
mozi.egg-info/SOURCES.txt
mozi.egg-info/dependency_links.txt
mozi.egg-info/not-zip-safe
mozi.egg-info/requires.txt
mozi.egg-info/top_level.txt
mozi/datasets/__init__.py
mozi/datasets/cifar10.py
mozi/datasets/cifar100.py
mozi/datasets/dataset.py
mozi/datasets/dataset_noise.py
mozi/datasets/imdb.py
mozi/datasets/iterator.py
mozi/datasets/mnist.py
mozi/datasets/preprocessor.py
mozi/datasets/voc.py
mozi/layers/__init__.py
mozi/layers/activation.py
mozi/layers/alexnet.py
mozi/layers/convolution.py
mozi/layers/embedding.py
mozi/layers/linear.py
mozi/layers/misc.py
mozi/layers/noise.py
mozi/layers/normalization.py
mozi/layers/preprocessor.py
mozi/layers/recurrent.py
mozi/layers/template.py
mozi/layers/vae.py
mozi/utils/__init__.py
mozi/utils/check_memory.py
mozi/utils/cnn_utils.py
mozi/utils/image.py
mozi/utils/mnist_utils.py
mozi/utils/progbar.py
mozi/utils/theano_utils.py
mozi/utils/train_object_utils.py
mozi/utils/utils.py