Metadata-Version: 1.0
Name: mozi
Version: 2.0.3
Summary: Deep learning package based on theano for building all kinds of models
Home-page: https://github.com/hycis/Mozi
Author: Wu Zhen Zhou
Author-email: hyciswu@gmail.com
License: The MIT License (MIT), see LICENCE
Platform: UNKNOWN
